uxml2dict/__init__.py
uxml2dict-0.2.2.dist-info/LICENSE
uxml2dict-0.2.2.dist-info/METADATA
uxml2dict-0.2.2.dist-info/WHEEL
uxml2dict-0.2.2.dist-info/entry_points.txt
uxml2dict-0.2.2.dist-info/top_level.txt
uxml2dict-0.2.2.dist-info/RECORD
